{
    "GENERAL":{
        "TIME": 3
    },
    "NETVY":{
        "URLBASE":"localhost",
        "USER":"testPaisEmpresa1706@gmail.com",
        "PASSWORD":"ferWUk",
        "LICENSE":"NETVY-TEST-LOCAL",
        "CODIGOFAMILIA":"FAMGE",
        "CODIGOMONEDA":"MXN"
    },
    "SQLLITE":{
        "DBPATH":"C:\\ProgramData\\SincronizadorContpaqi\\LocalDB\\SQLLITESincronizadorContpaqi.db",
        "DBPATH2":"./LocalDB/SQLLITESincronizadorContpaqi.db"
    },
    "CONTPAQ":{
        "PATH":"C:\\Program Files (x86)\\Compac\\COMERCIAL",
        "USER":"SUPERVISOR",
        "PASSWORD":"",
        "EMPRESA_ID": 2,
        "NOMBRE_PAQ":"CONTPAQ I COMERCIAL",
        "DRIVER":"{SQL Server}",
        "SERVER":"DESKTOP-HRHK2MO\\CONTPAQI",
        "DATABASE":"adREVISION",
        "Trusted_Connection":"no",
        "SQL_USER":"sa",
        "SQL_PASSWORD":"CONTPAQI2026"
    }
}